aspect/__init__.py
aspect/aspect.toml
aspect/changelog.txt
aspect/io.py
aspect/plots.py
aspect/tools.py
aspect/trainer.py
aspect/workflow.py
aspect/models/aspect_min-max-log_12_pixels_v10_model.joblib
aspect/models/aspect_min-max-log_12_pixels_v10_model.toml
aspect/models/aspect_min-max_12_pixels_v7_model.joblib
aspect/models/aspect_min-max_12_pixels_v7_model.toml
aspect_stable-0.5.1.dist-info/METADATA
aspect_stable-0.5.1.dist-info/WHEEL
aspect_stable-0.5.1.dist-info/top_level.txt
aspect_stable-0.5.1.dist-info/RECORD
